vllm/_C.abi3.so
vllm/__init__.py
vllm/_core_C.abi3.so
vllm/_core_ext.py
vllm/_custom_ops.py
vllm/_ipex_ops.py
vllm/_moe_C.abi3.so
vllm/_nm_C.abi3.so
vllm/_nm_ops.py
vllm/_version.py
vllm/beam_search.py
vllm/block.py
vllm/config.py
vllm/connections.py
vllm/envs.py
vllm/forward_context.py
vllm/logger.py
vllm/outputs.py
vllm/pooling_params.py
vllm/py.typed
vllm/sampling_params.py
vllm/scalar_type.py
vllm/scripts.py
vllm/sequence.py
vllm/tracing.py
vllm/utils.py
vllm/version.py
vllm/adapter_commons/__init__.py
vllm/adapter_commons/layers.py
vllm/adapter_commons/models.py
vllm/adapter_commons/request.py
vllm/adapter_commons/utils.py
vllm/adapter_commons/worker_manager.py
vllm/assets/__init__.py
vllm/assets/audio.py
vllm/assets/base.py
vllm/assets/image.py
vllm/assets/video.py
vllm/attention/__init__.py
vllm/attention/layer.py
vllm/attention/selector.py
vllm/attention/backends/__init__.py
vllm/attention/backends/abstract.py
vllm/attention/backends/blocksparse_attn.py
vllm/attention/backends/flash_attn.py
vllm/attention/backends/flashinfer.py
vllm/attention/backends/ipex_attn.py
vllm/attention/backends/openvino.py
vllm/attention/backends/pallas.py
vllm/attention/backends/placeholder_attn.py
vllm/attention/backends/rocm_flash_attn.py
vllm/attention/backends/torch_sdpa.py
vllm/attention/backends/utils.py
vllm/attention/backends/xformers.py
vllm/attention/ops/__init__.py
vllm/attention/ops/ipex_attn.py
vllm/attention/ops/paged_attn.py
vllm/attention/ops/prefix_prefill.py
vllm/attention/ops/triton_flash_attention.py
vllm/attention/ops/blocksparse_attention/__init__.py
vllm/attention/ops/blocksparse_attention/blocksparse_attention_kernel.py
vllm/attention/ops/blocksparse_attention/interface.py
vllm/attention/ops/blocksparse_attention/utils.py
vllm/compilation/__init__.py
vllm/compilation/backends.py
vllm/compilation/compile_context.py
vllm/compilation/decorators.py
vllm/compilation/levels.py
vllm/compilation/wrapper.py
vllm/core/__init__.py
vllm/core/block_manager_v1.py
nm_vllm-0.6.3.0.dist-info/LICENSE
nm_vllm-0.6.3.0.dist-info/LICENSE.apache
nm_vllm-0.6.3.0.dist-info/LICENSE.awq
nm_vllm-0.6.3.0.dist-info/LICENSE.fastertransformer
nm_vllm-0.6.3.0.dist-info/LICENSE.gptq
nm_vllm-0.6.3.0.dist-info/LICENSE.marlin
nm_vllm-0.6.3.0.dist-info/LICENSE.punica
nm_vllm-0.6.3.0.dist-info/LICENSE.squeezellm
nm_vllm-0.6.3.0.dist-info/LICENSE.tensorrtllm
nm_vllm-0.6.3.0.dist-info/LICENSE.vllm
nm_vllm-0.6.3.0.dist-info/METADATA
nm_vllm-0.6.3.0.dist-info/NOTICE
nm_vllm-0.6.3.0.dist-info/WHEEL
nm_vllm-0.6.3.0.dist-info/entry_points.txt
nm_vllm-0.6.3.0.dist-info/top_level.txt
nm_vllm-0.6.3.0.dist-info/RECORD
